setVCD/__init__.py
setVCD/exceptions.py
setVCD/py.typed
setVCD/setVCD.py
setVCD/types.py
setvcd-0.5.0.dist-info/licenses/LICENSE
setvcd-0.5.0.dist-info/METADATA
setvcd-0.5.0.dist-info/WHEEL
setvcd-0.5.0.dist-info/top_level.txt
setvcd-0.5.0.dist-info/RECORD
