Metadata-Version: 2.4
Name: setVCD
Version: 0.5.0
Summary: Convert VCD signals to sets of time points based on conditions
Author-email: Michail Rontionov <mrontionov@mront.io>
License: MIT
Project-URL: Homepage, https://github.com/mrontio/setVCD
Project-URL: Repository, https://github.com/mrontio/setVCD
Project-URL: Issues, https://github.com/mrontio/setVCD/issues
Keywords: vcd,verilog,waveform,signal,testing,verification
Classifier: Development Status :: 3 - Alpha
Classifier: Intended Audience :: Developers
Classifier: Topic :: Software Development :: Testing
Classifier: Topic :: System :: Hardware
Classifier: License :: OSI Approved :: MIT License
Classifier: Programming Language :: Python :: 3
Classifier: Programming Language :: Python :: 3.8
Classifier: Programming Language :: Python :: 3.9
Classifier: Programming Language :: Python :: 3.10
Classifier: Programming Language :: Python :: 3.11
Classifier: Programming Language :: Python :: 3.12
Classifier: Typing :: Typed
Requires-Python: >=3.8
License-File: LICENSE
Requires-Dist: vcdvcd>=2.0.0
Provides-Extra: dev
Requires-Dist: pytest>=7.0; extra == "dev"
Requires-Dist: pytest-cov>=4.0; extra == "dev"
Requires-Dist: mypy>=1.0; extra == "dev"
Requires-Dist: black>=23.0; extra == "dev"
Requires-Dist: ruff>=0.1.0; extra == "dev"
Requires-Dist: isort>=5.0; extra == "dev"
Dynamic: license-file
